./.gitignore
./PKG-INFO
./README.md
./pyproject.toml
./vision_agents/plugins/nvidia/__init__.py
./vision_agents/plugins/nvidia/events.py
./vision_agents/plugins/nvidia/nvidia_vlm.py
vision_agents_plugins_nvidia-0.2.10.dist-info/METADATA
vision_agents_plugins_nvidia-0.2.10.dist-info/WHEEL
vision_agents_plugins_nvidia-0.2.10.dist-info/RECORD
