Metadata-Version: 2.4
Name: vision-agents-plugins-nvidia
Version: 0.2.10
Summary: NVIDIA VLM plugin for Vision Agents
Project-URL: Documentation, https://visionagents.ai/
Project-URL: Website, https://visionagents.ai/
Project-URL: Source, https://github.com/GetStream/Vision-Agents
License-Expression: MIT
Keywords: AI,VLM,agents,nvcf,nvidia,vision agents
Requires-Python: >=3.10
Requires-Dist: aiohttp>=3.9.0
Requires-Dist: vision-agents
